rbase24-0.3.2.dist-info/METADATA
rbase24-0.3.2.dist-info/WHEEL
rbase24-0.3.2.dist-info/entry_points.txt
rbase24-0.3.2.dist-info/licenses/LICENSE
rbase24/__init__.py
rbase24/__main__.py
rbase24/cli.py
rbase24/color.py
rbase24/config.py
rbase24/scheme.py
rbase24/typedefs.py
rbase24-0.3.2.dist-info/RECORD
