Metadata-Version: 2.1
Name: rbase24
Version: 0.3.2
Summary: base16/base24 color scheme terminal viewer
Author-Email: Simon Kennedy <sffjunkie+code@gmail.com>
License: MIT
Project-URL: Homepage, https://github.com/sffjunkie/rbase24
Project-URL: Issues, https://github.com/sffjunkie/rbase24/issues
Requires-Python: >=3.11
Requires-Dist: rich
Requires-Dist: pyyaml
Requires-Dist: unicode-slugify
Requires-Dist: typer
